bloom.cpython-39-darwin.so
bloom.cpython-39-darwin.so.o
zig_bloom-0.0.7.dist-info/METADATA
zig_bloom-0.0.7.dist-info/WHEEL
zig_bloom-0.0.7.dist-info/top_level.txt
zig_bloom-0.0.7.dist-info/RECORD
