Metadata-Version: 2.1
Name: zig-bloom
Version: 0.0.7
Summary: Bloom filter implemented in zig
Home-page: https://github.com/Stefano-t/bloom-zig
Author: Stefano Taverni
Author-email: ste.taverni@gmail.com
License: BSD-3-Clause
Platform: UNKNOWN
